StonyBrook/ComputerArchitecture/Homework1/TailLight.v
module TailLight(input rst, input clk, input l, input r, 
output reg lc, output reg lb, output reg la, 
output reg ra, output reg rb, output reg rc);
    
    reg [3:0] state, nextState;
    
    // various states
    parameter INIT = 4'b0000;
    parameter RA = 4'b0001;
    parameter RAB = 4'b0011;
    parameter RABC = 4'b0111;
    parameter LA = 4'b1000;
    parameter LAB = 4'b1100;
    parameter LABC = 4'b1110;

    // handle state register update on clock cycle
    always @ (posedge clk) begin
        if(rst)
            state <= INIT;
        else
            state <= nextState;
    end

    // next state logic
    always @(*) begin
        case(state)
            INIT:   nextState = l ? LA : r ? RA : INIT;
            RA:     nextState = RAB;
            RAB:    nextState = RABC;
            RABC:   nextState = l ? LA : r ? RA : INIT;
            LA:     nextState = LAB;
            LAB:    nextState = LABC;
            LABC:   nextState = l ? LA : r ? RA : INIT;
            default:nextState = INIT;
        endcase
    end

    // Output logic
    always @(*) begin
        case(state)
            INIT: begin
                lc <= 0;
                lb <= 0;
                la <= 0;
                ra <= 0;
                rb <= 0;
                rc <= 0;
            end
            RA: begin
                lc <= 0;
                lb <= 0;
                la <= 0;
                ra <= 1;
                rb <= 0;
                rc <= 0;
            end
            RAB: begin
                lc <= 0;
                lb <= 0;
                la <= 0;
                ra <= 1;
                rb <= 1;
                rc <= 0;
            end
            RABC: begin
                lc <= 0;
                lb <= 0;
                la <= 0;
                ra <= 1;
                rb <= 1;
                rc <= 1;
            end
            LA: begin
                lc <= 0;
                lb <= 0;
                la <= 1;
                ra <= 0;
                rb <= 0;
                rc <= 0;
            end
            LAB: begin
                lc <= 0;
                lb <= 1;
                la <= 1;
                ra <= 0;
                rb <= 0;
                rc <= 0;
            end
            LABC: begin
                lc <= 1;
                lb <= 1;
                la <= 1;
                ra <= 0;
                rb <= 0;
                rc <= 0;
            end
            default: begin
                lc <= 0;
                lb <= 0;
                la <= 0;
                ra <= 0;
                rb <= 0;
                rc <= 0;
            end
        endcase
    end

endmodule

StonyBrook/ComputerArchitecture/Homework1/TailLight_tb.v
`timescale 1ns / 1ps

module TailLight_tb;

    reg clock;
    reg reset;
    reg left;
    reg right;
    wire la;
    wire lb;
    wire lc;
    wire ra;
    wire rb;
    wire rc;

    TailLight tail(reset, clock, left, right, lc, lb, la, ra, rb, rc);

    initial begin
        $dumpfile("test_tail.vcd");
        $dumpvars(0, TailLight_tb);
        clock = 0;
        forever #5 clock = ~clock;
    end
    initial begin
        reset = 1;
        left = 0;
        right = 0; // set all values to default
        #10;
        reset = 0; // reset back to 0
        #10;
        left = 1; // start left case
        #10;
        left = 0;
        #30;
        right = 1; // start right case
        #10;
        right = 0;
        #30;
        left = 1; // start left case
        #10;
        left = 0;
        #10;
        reset = 1; // manual reset during left case
        #10;
        reset = 0;
        #10;
        right = 1; // start right case
        #10;
        right = 0;
        #10;
        reset = 1; // manual reset during right case
        #10;
        reset = 0;
        #10;
        left = 1; // testing priority left if both signals are on
        right = 1;
        reset = 1;
        #10;
        reset = 0;
        #10;
        left = 0;
        right = 0;
        #30;
        left = 1; // testing if left can immediate transition back to left
        #40;
        left = 0;
        #20;
        left = 1; // testing if right is triggered during left, nothing happens until after
        #10;
        left = 0;
        right = 1;
        #40;
        right = 0;
        left = 1;
        #30;
        left = 0;
        #30;
        reset = 1;
        #10;
        reset = 0;

        $finish;
    end

endmodule

StonyBrook/ComputerArchitecture/Homework1/test_tail.vcd
$date
	Sun Sep 28 19:47:57 2025
$end
$version
	Icarus Verilog
$end
$timescale
	1ps
$end
$scope module TailLight_tb $end
$var wire 1 ! rc $end
$var wire 1 " rb $end
$var wire 1 # ra $end
$var wire 1 $ lc $end
$var wire 1 % lb $end
$var wire 1 & la $end
$var reg 1 ' clock $end
$var reg 1 ( left $end
$var reg 1 ) reset $end
$var reg 1 * right $end
$scope module tail $end
$var wire 1 ' clk $end
$var wire 1 ( l $end
$var wire 1 * r $end
$var wire 1 ) rst $end
$var reg 1 & la $end
$var reg 1 % lb $end
$var reg 1 $ lc $end
$var reg 4 + nextState [3:0] $end
$var reg 1 # ra $end
$var reg 1 " rb $end
$var reg 1 ! rc $end
$var reg 4 , state [3:0] $end
$upscope $end
$upscope $end
$enddefinitions $end
#0
$dumpvars
bx ,
b0 +
0*
1)
0(
0'
x&
x%
x$
x#
x"
x!
$end
#5000
0!
0"
0#
0&
0%
0$
b0 ,
1'
#10000
0'
0)
#15000
1'
#20000
b1000 +
0'
1(
#25000
1&
b1100 +
b1000 ,
1'
#30000
0'
0(
#35000
1%
b1110 +
b1100 ,
1'
#40000
0'
#45000
1$
b0 +
b1110 ,
1'
#50000
0'
#55000
0&
0%
0$
b0 ,
1'
#60000
b1 +
0'
1*
#65000
1#
b11 +
b1 ,
1'
#70000
0'
0*
#75000
1"
b111 +
b11 ,
1'
#80000
0'
#85000
1!
b0 +
b111 ,
1'
#90000
0'
#95000
0!
0"
0#
b0 ,
1'
#100000
b1000 +
0'
1(
#105000
1&
b1100 +
b1000 ,
1'
#110000
0'
0(
#115000
1%
b1110 +
b1100 ,
1'
#120000
0'
1)
#125000
0&
0%
b0 +
b0 ,
1'
#130000
0'
0)
#135000
1'
#140000
b1 +
0'
1*
#145000
1#
b11 +
b1 ,
1'
#150000
0'
0*
#155000
1"
b111 +
b11 ,
1'
#160000
0'
1)
#165000
0"
0#
b0 +
b0 ,
1'
#170000
0'
0)
#175000
1'
#180000
b1000 +
0'
1)
1*
1(
#185000
1'
#190000
0'
0)
#195000
1&
b1100 +
b1000 ,
1'
#200000
0'
0*
0(
#205000
1%
b1110 +
b1100 ,
1'
#210000
0'
#215000
1$
b0 +
b1110 ,
1'
#220000
0'
#225000
0&
0%
0$
b0 ,
1'
#230000
b1000 +
0'
1(
#235000
1&
b1100 +
b1000 ,
1'
#240000
0'
#245000
1%
b1110 +
b1100 ,
1'
#250000
0'
#255000
1$
b1000 +
b1110 ,
1'
#260000
0'
#265000
0%
0$
b1100 +
b1000 ,
1'
#270000
0'
0(
#275000
1%
b1110 +
b1100 ,
1'
#280000
0'
#285000
1$
b0 +
b1110 ,
1'
#290000
b1000 +
0'
1(
#295000
0%
0$
b1100 +
b1000 ,
1'
#300000
0'
1*
0(
#305000
1%
b1110 +
b1100 ,
1'
#310000
0'
#315000
1$
b1 +
b1110 ,
1'
#320000
0'
#325000
1#
0&
0%
0$
b11 +
b1 ,
1'
#330000
0'
#335000
1"
b111 +
b11 ,
1'
#340000
0'
1(
0*
#345000
1!
b1000 +
b111 ,
1'
#350000
0'
#355000
0!
0"
0#
1&
b1100 +
b1000 ,
1'
#360000
0'
#365000
1%
b1110 +
b1100 ,
1'
#370000
0'
0(
#375000
1$
b0 +
b1110 ,
1'
#380000
0'
#385000
0&
0%
0$
b0 ,
1'
#390000
0'
#395000
1'
#400000
0'
1)
#405000
1'
#410000
0'
0)
