StonyBrook/ComputerArchitecture/Homework1.v
module FullAdder(input a, input b, input ci, output s, output co);
    /*
    Implement a full adder using verilog
    */
    assign s = a ^ b ^ ci;
    assign co = (a & b) | (b & ci) | (a & ci);

endmodule

module test;
reg a,b,cin;
wire s,co;


FullAdder adder(a,b,cin,s,co);

initial begin
    $dumpfile("test.vcd");
    $dumpvars(0,test);
    a = 0; b = 0; cin = 0;
    #10
    a = 0; b = 0; cin = 1;
    #10
    a = 0; b = 1; cin = 0;
    #10
    a = 0; b = 1; cin = 1;
    #10
    a = 1; b = 0; cin = 0;
    #10
    a = 1; b = 0; cin = 1;
    #10
    a = 1; b = 1; cin = 0;
    #10
    a = 1; b = 1; cin = 1;
    #10 
    $finish();
end

initial
begin
   $dumpfile("test.vcd");
   $dumpvars(0,test);
end
                
endmodule

StonyBrook/ComputerArchitecture/test.vcd
$date
	Tue Sep 23 17:22:05 2025
$end
$version
	Icarus Verilog
$end
$timescale
	1s
$end
$scope module test $end
$var wire 1 ! s $end
$var wire 1 " co $end
$var reg 1 # a $end
$var reg 1 $ b $end
$var reg 1 % cin $end
$scope module adder $end
$var wire 1 # a $end
$var wire 1 $ b $end
$var wire 1 % ci $end
$var wire 1 " co $end
$var wire 1 ! s $end
$upscope $end
$upscope $end
$scope module test $end
$scope module adder $end
$upscope $end
$upscope $end
$enddefinitions $end
#0
$dumpvars
0%
0$
0#
0"
0!
$end
#10
1!
1%
#20
0%
1$
#30
1"
0!
1%
#40
0"
1!
0%
0$
1#
#50
1"
0!
1%
#60
0%
1$
#70
1!
1%
